CODE_OF_CONDUCT.md
CONTRIBUTING.rst
LICENSE
MANIFEST.in
README.rst
setup.cfg
setup.py
doc/Makefile
doc/api.rst
doc/basic_use.rst
doc/changelog.rst
doc/conf.py
doc/future.rst
doc/incompatibilities.rst
doc/index.rst
doc/installation.rst
doc/make.bat
doc/output.rst
doc/images/sample_plotmetric.png
instrument/__init__.py
instrument.egg-info/PKG-INFO
instrument.egg-info/SOURCES.txt
instrument.egg-info/dependency_links.txt
instrument.egg-info/requires.txt
instrument.egg-info/top_level.txt
instrument/output/__init__.py
instrument/output/_numpy.py
instrument/output/csv.py
instrument/output/logging.py
instrument/output/plot.py
instrument/output/statsd.py
instrument/output/table.py
tests/__init__.py
tests/test_csv.py
tests/test_plot.py
tests/test_table.py