Metadata-Version: 2.1
Name: instrument
Version: 0.6.0
Summary: instrumentation primitives for metrics and benchmarking
Home-page: http://github.com/wearpants/instrument
Author: Pete Fein
Author-email: pete@wearpants.org
License: BSD
Platform: UNKNOWN
Classifier: Programming Language :: Python :: 3
Classifier: Development Status :: 5 - Production/Stable
Classifier: Intended Audience :: Developers
Classifier: License :: OSI Approved :: BSD License
Provides-Extra: numpy
Provides-Extra: statsd
Provides-Extra: plot
